bias_adjustment/__init__.py
bias_adjustment/bias_adjustment.py
bias_adjustment/const.py
bias_adjustment/distributions/__init__.py
bias_adjustment/distributions/distributions.py
bias_adjustment/quantile_mapping/__init__.py
bias_adjustment/quantile_mapping/dqm.py
bias_adjustment/quantile_mapping/qdm.py
bias_adjustment/quantile_mapping/qm.py
bias_adjustment/utils.py
bias_adjustment-1.0.6.dist-info/WHEEL
bias_adjustment-1.0.6.dist-info/METADATA
bias_adjustment-1.0.6.dist-info/LICENSE
bias_adjustment-1.0.6.dist-info/RECORD
