Metadata-Version: 2.1
Name: bias-adjustment
Version: 1.0.6
Summary: Bias Adjusment by Quantile Mapping
Home-page: https://github.com/emiliogozo/bias_adjustment
License: MIT
Keywords: climatology,data analysis,quantile mapping,bias correction
Author: Emilio Gozo
Author-email: emiliogozo@proton.me
Requires-Python: >=3.8.1,<3.9
Classifier: License :: OSI Approved :: MIT License
Classifier: Programming Language :: Python :: 3
Requires-Dist: conda-lock (>=1.4.0,<2.0.0)
Requires-Dist: numpy (>=1.24.3,<2.0.0)
Requires-Dist: scipy (>=1.9.3,<2.0.0)
Project-URL: Repository, https://github.com/emiliogozo/bias_adjustment
